persona_integration/__init__.py
persona_integration/admin.py
persona_integration/api.py
persona_integration/apps.py
persona_integration/exceptions.py
persona_integration/models.py
persona_integration/statuses.py
persona_integration/urls.py
persona_integration/utils.py
persona_integration/views.py
persona_integration/migrations/0001_initial.py
persona_integration/migrations/0002_verificationattempt.py
persona_integration/migrations/0003_verificationattempt_event_created_at_and_more.py
persona_integration/migrations/0004_alter_userpersonaaccount_user.py
persona_integration/migrations/0005_verificationattempt_platform_verification_attempt_id.py
persona_integration/migrations/0006_alter_verificationattempt_user.py
persona_integration/migrations/0007_alter_verificationattempt_event_created_at_and_more.py
persona_integration/migrations/__init__.py
persona_integration/signals/__init__.py
persona_integration/signals/handlers.py
persona_integration/templates/persona_integration/base.html
persona_integration/test_utils/__init__.py
persona_integration/test_utils/factories.py
persona_integration/test_utils/utils.py
persona_integration-3.2.2.dist-info/licenses/LICENSE
persona_integration-3.2.2.dist-info/licenses/LICENSE.txt
persona_integration-3.2.2.dist-info/METADATA
persona_integration-3.2.2.dist-info/WHEEL
persona_integration-3.2.2.dist-info/entry_points.txt
persona_integration-3.2.2.dist-info/top_level.txt
persona_integration-3.2.2.dist-info/RECORD
