Metadata-Version: 2.4
Name: persona-integration
Version: 3.2.2
Summary: This repo contains the backend plugin that implements the Persona integration to be used for id
Home-page: https://github.com/edx/persona-integration
Author: 2U, Inc.
Author-email: team-cosmonauts@edx.org
License: AGPL 3.0
Keywords: Python edx
Classifier: Development Status :: 3 - Alpha
Classifier: Framework :: Django
Classifier: Framework :: Django :: 4.2
Classifier: Framework :: Django :: 5.2
Classifier: Intended Audience :: Developers
Classifier: License :: OSI Approved :: GNU Affero General Public License v3 or later (AGPLv3+)
Classifier: Natural Language :: English
Classifier: Programming Language :: Python :: 3
Classifier: Programming Language :: Python :: 3.11
Classifier: Programming Language :: Python :: 3.12
Requires-Python: >=3.11
License-File: LICENSE
License-File: LICENSE.txt
Requires-Dist: Django
Requires-Dist: django-model-utils
Requires-Dist: djangorestframework
Requires-Dist: edx-drf-extensions
Requires-Dist: openedx-atlas
Dynamic: author
Dynamic: author-email
Dynamic: classifier
Dynamic: description
Dynamic: home-page
Dynamic: keywords
Dynamic: license
Dynamic: license-file
Dynamic: requires-dist
Dynamic: requires-python
Dynamic: summary
